ProvSense/__init__.py
ProvSense/app.py
ProvSense/cli.py
ProvSense/shared.py
provsense-1.0.2.dist-info/LICENSE.txt
provsense-1.0.2.dist-info/METADATA
provsense-1.0.2.dist-info/WHEEL
provsense-1.0.2.dist-info/entry_points.txt
provsense-1.0.2.dist-info/RECORD
